typesplainer/__init__.py
typesplainer/__main__.py
typesplainer/core.py
typesplainer-0.2.6.dist-info/LICENSE
typesplainer-0.2.6.dist-info/METADATA
typesplainer-0.2.6.dist-info/WHEEL
typesplainer-0.2.6.dist-info/top_level.txt
typesplainer-0.2.6.dist-info/RECORD
